udica/__init__.py
udica/__main__.py
udica/parse.py
udica/perms.py
udica/policy.py
udica-0.1.6.dist-info/METADATA
udica-0.1.6.dist-info/RECORD
udica-0.1.6.dist-info/WHEEL
udica-0.1.6.dist-info/entry_points.txt
udica-0.1.6.dist-info/top_level.txt
usr/share/licenses/udica/LICENSE
usr/share/udica/templates/base_container.cil
usr/share/udica/templates/config_container.cil
usr/share/udica/templates/home_container.cil
usr/share/udica/templates/log_container.cil
usr/share/udica/templates/net_container.cil
usr/share/udica/templates/tmp_container.cil
usr/share/udica/templates/tty_container.cil
usr/share/udica/templates/virt_container.cil
usr/share/udica/templates/x_container.cil
