Metadata-Version: 2.1
Name: udica
Version: 0.1.6
Summary: A tool for generating SELinux security policies for containers
Home-page: https://github.com/containers/udica
Author: Lukas Vrabec
Author-email: lvrabec@redhat.com
License: GPLv3+
Platform: UNKNOWN
Classifier: Programming Language :: Python :: 3
Classifier: License :: OSI Approved :: GNU General Public License v3 or later (GPLv3+)
Classifier: Operating System :: OS Independent
